v_log/__init__.py
v_log/constants.py
v_log/utilities.py
v_log/v_log.py
v_log-1.0.1.dist-info/LICENSE.txt
v_log-1.0.1.dist-info/METADATA
v_log-1.0.1.dist-info/WHEEL
v_log-1.0.1.dist-info/top_level.txt
v_log-1.0.1.dist-info/RECORD
