Metadata-Version: 2.1
Name: v-log
Version: 1.0.1
Summary: Colored log that also stores a properly formated csv.
Home-page: https://github.com/villoro/v-log
Author: Arnau Villoro
Author-email: arnau@villoro.com
License: MIT
Platform: UNKNOWN
Classifier: Intended Audience :: Developers
Classifier: Intended Audience :: Education
Classifier: Intended Audience :: Manufacturing
Classifier: Intended Audience :: Science/Research
Classifier: License :: OSI Approved :: MIT License
Classifier: Programming Language :: Python
Classifier: Programming Language :: Python :: 3.6
Requires-Dist: colorama
Requires-Dist: termcolor
